assisting_functions/__init__.py
assisting_functions/functions.py
models/GBRS_vanilla.py
models/__init__.py
GBRSS-0.0.0.2.dist-info/METADATA
GBRSS-0.0.0.2.dist-info/WHEEL
GBRSS-0.0.0.2.dist-info/top_level.txt
GBRSS-0.0.0.2.dist-info/RECORD
