Metadata-Version: 2.1
Name: GBRSS
Version: 0.0.0.2
Summary: The GBRSs Module Series
Home-page: UNKNOWN
Author: Longyin Cui
Author-email: <cuilongyin@hotmail.com>
License: UNKNOWN
Keywords: python,recommender systems,privacy preserving
Platform: UNKNOWN
Classifier: Development Status :: 3 - Alpha
Classifier: Intended Audience :: Education
Classifier: Programming Language :: Python :: 3
Classifier: Operating System :: MacOS :: MacOS X
Classifier: Operating System :: Microsoft :: Windows
Requires-Dist: surprise
Requires-Dist: pandas
Requires-Dist: numpy
